<?xml version="1.0" encoding="utf-8" ?><dwsync><file name="about.htm" server="192.168.0.69//Applications/MAMP/htdocs/cocina/" local="3460867462" remote="12052834532" /><file name="anchor.htm" server="192.168.0.69//Applications/MAMP/htdocs/cocina/" local="3460867462" remote="12052834532" /><file name="charmap.htm" server="192.168.0.69//Applications/MAMP/htdocs/cocina/" local="3460867462" remote="12052834532" /><file name="color_picker.htm" server="192.168.0.69//Applications/MAMP/htdocs/cocina/" local="3460867462" remote="12052834532" /><file name="editor_template.js" server="192.168.0.69//Applications/MAMP/htdocs/cocina/" local="3460867462" remote="12052834532" /><file name="editor_template_src.js" server="192.168.0.69//Applications/MAMP/htdocs/cocina/" local="3460867462" remote="12052834532" /><file name="image.htm" server="192.168.0.69//Applications/MAMP/htdocs/cocina/" local="3460867462" remote="12052834532" /><file name="link.htm" server="192.168.0.69//Applications/MAMP/htdocs/cocina/" local="3460867462" remote="12052834532" /><file name="shortcuts.htm" server="192.168.0.69//Applications/MAMP/htdocs/cocina/" local="3460867462" remote="12052834532" /><file name="source_editor.htm" server="192.168.0.69//Applications/MAMP/htdocs/cocina/" local="3460867462" remote="12052834532" /></dwsync>